QuarchpyQCS/Custom_test_variable.py
QuarchpyQCS/Drive_wrapper.py
QuarchpyQCS/SmartCTLController.py
QuarchpyQCS/__init__.py
QuarchpyQCS/__main__.py
QuarchpyQCS/_version.py
QuarchpyQCS/_version.py.bak
QuarchpyQCS/base_test.py
QuarchpyQCS/driveTestConfig.py
QuarchpyQCS/driveTestCore.py
QuarchpyQCS/dtsComms.py
QuarchpyQCS/dtsGlobals.py
QuarchpyQCS/hostInformation.py
QuarchpyQCS/lspci.py
QuarchpyQCS/sasFuncs.py
QuarchpyQCS/testLine.py
QuarchpyQCS/Docs/CHANGES.rst
QuarchpyQCS/Docs/Makefile
QuarchpyQCS/Docs/conf.py
QuarchpyQCS/Docs/make.bat
QuarchpyQCS/Docs/readme.rst
QuarchpyQCS/Docs/source/changelog.rst
QuarchpyQCS/certs/client_cert.pem
QuarchpyQCS/certs/server_cert.pem
QuarchpyQCS/certs/server_key.key
QuarchpyQCS/pciutils/DirectIOLib32.dll
QuarchpyQCS/pciutils/hostInformation.py
QuarchpyQCS/pciutils/lspci.exe
QuarchpyQCS/pciutils/pci.ids.gz
QuarchpyQCS/pciutils/setpci.exe
QuarchpyQCS/pciutils/update-pciids.cmd
QuarchpyQCS/pciutils/.idea/encodings.xml
QuarchpyQCS/pciutils/.idea/misc.xml
QuarchpyQCS/pciutils/.idea/modules.xml
QuarchpyQCS/pciutils/.idea/pciutils.iml
QuarchpyQCS/pciutils/.idea/workspace.xml
QuarchpyQCS/pciutils/doc/COPYING
QuarchpyQCS/pciutils/doc/lspci.html
QuarchpyQCS/pciutils/doc/pcilib.html
QuarchpyQCS/pciutils/doc/setpci.html
QuarchpyQCS/smartmontools/uninst-smartmontools.exe
QuarchpyQCS/smartmontools/bin/drivedb.h
QuarchpyQCS/smartmontools/bin/runcmdu.exe
QuarchpyQCS/smartmontools/bin/smartctl-nc.exe
QuarchpyQCS/smartmontools/bin/smartctl.exe
QuarchpyQCS/smartmontools/bin/smartd.conf
QuarchpyQCS/smartmontools/bin/smartd.exe
QuarchpyQCS/smartmontools/bin/smartd_mailer.conf.sample.ps1
QuarchpyQCS/smartmontools/bin/smartd_mailer.ps1
QuarchpyQCS/smartmontools/bin/smartd_warning.cmd
QuarchpyQCS/smartmontools/bin/update-smart-drivedb.ps1
QuarchpyQCS/smartmontools/bin/wtssendmsg.exe
QuarchpyQCS/smartmontools/doc/AUTHORS.txt
QuarchpyQCS/smartmontools/doc/COPYING.txt
QuarchpyQCS/smartmontools/doc/ChangeLog-6.0-7.0.txt
quarchqcs-1.1.5.dist-info/METADATA
quarchqcs-1.1.5.dist-info/WHEEL
quarchqcs-1.1.5.dist-info/top_level.txt
quarchqcs-1.1.5.dist-info/RECORD
