Metadata-Version: 2.1
Name: quarchqcs
Version: 1.1.5
Summary: This packpage contains the Quarch Compliance suite server
Author: Quarch Technology ltd
Author-email: support@quarch.com
License: Quarch Technology ltd
Keywords: quarch quarchpy QCS torridon
Classifier: Intended Audience :: Information Technology
Classifier: Intended Audience :: Developers
Classifier: Natural Language :: English
Classifier: Operating System :: MacOS
Classifier: Operating System :: Microsoft :: Windows
Classifier: Operating System :: POSIX
Classifier: Programming Language :: Python
Classifier: Topic :: Scientific/Engineering :: Information Analysis
Classifier: Topic :: System
Classifier: Topic :: System :: Power (UPS)
Requires-Dist: quarchpy (>=2.1.11)
Requires-Dist: numpy
Requires-Dist: pandas
